clickhouse_mcp_server/__init__.py
clickhouse_mcp_server/server.py
clickhouse_mcp_server-0.1.0.dist-info/METADATA
clickhouse_mcp_server-0.1.0.dist-info/WHEEL
clickhouse_mcp_server-0.1.0.dist-info/entry_points.txt
clickhouse_mcp_server-0.1.0.dist-info/licenses/LICENSE
clickhouse_mcp_server-0.1.0.dist-info/RECORD
