Metadata-Version: 2.4
Name: clickhouse-mcp-server
Version: 0.1.0
Summary: A MCP server implementation for ClickHouse database integration
Project-URL: Homepage, https://github.com/burakdirin/clickhouse-mcp-server
Project-URL: Repository, https://github.com/burakdirin/clickhouse-mcp-server
Project-URL: Bug Tracker, https://github.com/burakdirin/clickhouse-mcp-server/issues
Author-email: Burak Dirin <burakdirin@gmail.com>
License-Expression: MIT
License-File: LICENSE
Requires-Python: >=3.11
Requires-Dist: clickhouse-driver>=0.2.9
Requires-Dist: mcp>=1.4.1
Requires-Dist: python-dotenv>=1.0.1
